hermes_cai/__init__.py
hermes_cai/constants.py
hermes_cai/data.py
hermes_cai/decorators.py
hermes_cai/engine.py
hermes_cai/exceptions.py
hermes_cai/metrics.py
hermes_cai/remote_clients.py
hermes_cai/structured_prefix.py
hermes_cai/template_helpers.py
hermes_cai/test_engine.py
hermes_cai/contrib/__init__.py
hermes_cai/contrib/lm_prefix_utils.py
hermes_cai/contrib/test_parse_character_definition.py
hermes_cai/contrib/__pycache__/__init__.cpython-312.pyc
hermes_cai/contrib/__pycache__/__init__.cpython-313.pyc
hermes_cai/contrib/__pycache__/lm_prefix_utils.cpython-312.pyc
hermes_cai/contrib/__pycache__/lm_prefix_utils.cpython-313.pyc
hermes_cai/contrib/__pycache__/test_parse_character_definition.cpython-312-pytest-8.3.3.pyc
hermes_cai/templates/dynamic_greeting.yml.j2
hermes_cai/templates/production.yml.j2
hermes_cai/templates/production_raw.yml.j2
hermes_cai/templates/remove_persona.yml.j2
hermes_cai/templates/test.yml.j2
hermes_cai/templates/macros/global_settings.yml.j2
hermes_cai/templates/sections/audio_mode_instruction.yml.j2
hermes_cai/templates/sections/bod_timestamp.yml.j2
hermes_cai/templates/sections/character_definition_raw.yml.j2
hermes_cai/templates/sections/character_greeting.yml.j2
hermes_cai/templates/sections/chat_context_message_pins_raw.yml.j2
hermes_cai/templates/sections/chat_context_messages_raw.yml.j2
hermes_cai/templates/sections/chat_history.yml.j2
hermes_cai/templates/sections/facts.yml.j2
hermes_cai/templates/sections/persona_definition_raw.yml.j2
hermes_cai/templates/sections/pinned_history.yml.j2
hermes_cai/templates/sections/reply_prompt.yml.j2
hermes_cai/templates/sections/scene_definition_raw.yml.j2
hermes_cai/templates/sections/validate_inputs.yml.j2
hermes_cai-0.0.133.dist-info/METADATA
hermes_cai-0.0.133.dist-info/WHEEL
hermes_cai-0.0.133.dist-info/top_level.txt
hermes_cai-0.0.133.dist-info/RECORD
