Metadata-Version: 2.4
Name: hermes-cai
Version: 0.0.133
Summary: The simplest way of using control flow (like if statements and for loops) to build production-grade prompts for LLMs.
Home-page: https://github.com/character-tech/chat-stack
Author: James Groeneveld
Author-email: james@character.ai
License: MIT
Requires-Python: >=3.10
Requires-Dist: prompt-poet==0.0.50
Requires-Dist: prometheus-client==0.20.0
Requires-Dist: pydantic>=2.7.4
Dynamic: author
Dynamic: author-email
Dynamic: description
Dynamic: description-content-type
Dynamic: home-page
Dynamic: license
Dynamic: requires-dist
Dynamic: requires-python
Dynamic: summary
